{"services": {"0": {"stops": [{"time": 320, "station": "Retiro", "type": "D"}, {"time": 344, "station": "Tigre", "type": "A"}], "demand": [1087]}, "1": {"stops": [{"time": 433, "station": "Tigre", "type": "D"}, {"time": 457, "station": "Retiro", "type": "A"}], "demand": [1848]}, "2": {"stops": [{"time": 532, "station": "Retiro", "type": "D"}, {"time": 556, "station": "Tigre", "type": "A"}], "demand": [1702]}, "3": {"stops": [{"time": 659, "station": "Tigre", "type": "D"}, {"time": 683, "station": "Retiro", "type": "A"}], "demand": [1350]}, "4": {"stops": [{"time": 765, "station": "Retiro", "type": "D"}, {"time": 789, "station": "Tigre", "type": "A"}], "demand": [1277]}, "5": {"stops": [{"time": 277, "station": "Tigre", "type": "D"}, {"time": 301, "station": "Retiro", "type": "A"}], "demand": [1511]}, "6": {"stops": [{"time": 412, "station": "Retiro", "type": "D"}, {"time": 436, "station": "Tigre", "type": "A"}], "demand": [1806]}, "7": {"stops": [{"time": 523, "station": "Tigre", "type": "D"}, {"time": 547, "station": "Retiro", "type": "A"}], "demand": [1496]}, "8": {"stops": [{"time": 656, "station": "Retiro", "type": "D"}, {"time": 680, "station": "Tigre", "type": "A"}], "demand": [1422]}, "9": {"stops": [{"time": 761, "station": "Tigre", "type": "D"}, {"time": 785, "station": "Retiro", "type": "A"}], "demand": [1783]}}, "stations": ["Retiro", "Tigre"], "cost_per_unit": {"Tigre": 1.0, "Retiro": 1.0}, "rs_info": {"capacity": 100, "max_rs": 25}}